measure_exec_time/LICENSE
measure_exec_time/README.MD
measure_exec_time/__init__.py
measure_exec_time/requirements.txt
measure_exec_time/thirdparty.json
measure_exec_time-0.10.dist-info/LICENSE.rst
measure_exec_time-0.10.dist-info/METADATA
measure_exec_time-0.10.dist-info/WHEEL
measure_exec_time-0.10.dist-info/top_level.txt
measure_exec_time-0.10.dist-info/RECORD
